ctpysql.py
ctpysql-1.4.5.dist-info/LICENSE
ctpysql-1.4.5.dist-info/METADATA
ctpysql-1.4.5.dist-info/WHEEL
ctpysql-1.4.5.dist-info/top_level.txt
ctpysql-1.4.5.dist-info/RECORD
