Metadata-Version: 2.1
Name: ctpysql
Version: 1.4.5
Summary: This library helps you run MYSQL queries as fast as possible 🚄🔥!
Home-page: https://github.com/MahyarNV/cautious-pysql
Author: Mahyar Behzadi
Author-email: mahyarbhz@gmail.com
License: UNKNOWN
Platform: UNKNOWN
Requires-Dist: mysql-connector (>=2.2.9)
Requires-Dist: mysql-connector-python (>=8.0.23)
Provides-Extra: dev
Requires-Dist: pytest (>=6.2.2) ; extra == 'dev'
